avtagent/__init__.py
avtagent/agents.py
avtagent-0.1.5.dist-info/METADATA
avtagent-0.1.5.dist-info/WHEEL
avtagent-0.1.5.dist-info/top_level.txt
avtagent-0.1.5.dist-info/RECORD
