Metadata-Version: 2.1
Name: avtagent
Version: 0.1.5
Summary: A library for avt agent
Home-page: https://github.com/AvnetGIS/bcs-oco-agent-lib.git
Author: Harry Wang
Author-email: lajja.khakhkhar@avtinc.onmicrosoft.com
Classifier: Programming Language :: Python :: 3
Classifier: License :: OSI Approved :: MIT License
Classifier: Operating System :: OS Independent
Requires-Python: >=3.10
Requires-Dist: openai
Requires-Dist: pyautogen
